[{"loss": 0.9595340277467456, "y_true": [[0], [0], [1], [1], [0], [0], [1], [0], [1], [1], [0], [0], [0], [1], [1], [0], [0], [1], [0], [0], [2]], "y_pred": [[2], [2], [1], [1], [2], [2], [1], [2], [1], [1], [0], [1], [1], [2], [1], [1], [0], [1], [1], [0], [0]]}, {"loss": 0.8903077289462089, "y_true": [[1], [1], [1], [0], [0], [0], [0], [0], [0], [2], [0], [0], [1], [1], [1], [0], [1], [0], [0], [0]], "y_pred": [[0], [1], [1], [0], [1], [0], [0], [0], [0], [2], [0], [0], [0], [1], [1], [1], [0], [0], [0], [0]]}, {"loss": 0.9116958230733871, "y_true": [[0], [1], [1], [2], [1], [0], [1], [0], [1], [0], [1], [0], [0], [0], [0], [1], [1], [0], [0], [0]], "y_pred": [[1], [1], [1], [2], [1], [1], [1], [0], [1], [0], [0], [0], [1], [0], [1], [0], [1], [0], [1], [2]]}, {"loss": 1.1910910472273826, "y_true": [[0], [1], [1], [0], [0], [0], [1], [0], [0], [1], [0], [2], [0], [1], [0], [0], [1], [1], [0], [1]], "y_pred": [[1], [1], [1], [0], [1], [1], [1], [0], [1], [1], [0], [1], [1], [0], [2], [0], [1], [0], [1], [1]]}, {"loss": 0.949633501470089, "y_true": [[0], [0], [2], [1], [0], [0], [1], [1], [1], [1], [0], [0], [1], [1], [0], [0], [0], [0], [1], [0]], "y_pred": [[0], [1], [1], [1], [1], [0], [1], [1], [1], [1], [1], [2], [0], [0], [1], [1], [1], [0], [1], [1]]}]